flipper_raw_rfid/__init__.py
flipper_raw_rfid/bits.py
flipper_raw_rfid/cli.py
flipper_raw_rfid/rifl.py
flipper_raw_rfid/stuff.py
flipper_raw_rfid/utils.py
flipper_raw_rfid-0.2.dist-info/LICENSE
flipper_raw_rfid-0.2.dist-info/METADATA
flipper_raw_rfid-0.2.dist-info/WHEEL
flipper_raw_rfid-0.2.dist-info/entry_points.txt
flipper_raw_rfid-0.2.dist-info/top_level.txt
flipper_raw_rfid-0.2.dist-info/RECORD
