Metadata-Version: 2.1
Name: flipper-raw-rfid
Version: 0.2
Summary: A library for reading and analyzing Flipper Zero raw RFID files
Home-page: https://github.com/hnesk/flipper-raw-rfid
Author: Johannes Künsebeck
Author-email: kuensebeck@googlemail.com
License: MIT License
Keywords: flipper-zero,flipper,RFID
Classifier: Programming Language :: Python :: 3.8
Classifier: Programming Language :: Python :: 3.9
Classifier: Programming Language :: Python :: 3.10
Classifier: License :: OSI Approved :: MIT License
Classifier: Development Status :: 5 - Production/Stable
Classifier: Intended Audience :: Developers
Classifier: Intended Audience :: Science/Research
Requires-Python: >=3.8
License-File: LICENSE
Requires-Dist: numpy
Requires-Dist: scipy
Requires-Dist: docopt
